watchlog/__init__.py
watchlog/client.py
watchlog_python-0.1.3.dist-info/METADATA
watchlog_python-0.1.3.dist-info/WHEEL
watchlog_python-0.1.3.dist-info/top_level.txt
watchlog_python-0.1.3.dist-info/RECORD
