Metadata-Version: 2.1
Name: watchlog-python
Version: 0.1.3
Summary: A simple Python package for logging metrics.
Home-page: https://github.com/watchlogserver/watchlog-python
Author: mohammad
Author-email: mohammadnajm75@gmail.com
License: MIT License
Classifier: Environment :: Web Environment
Classifier: Framework :: Django
Classifier: Intended Audience :: Developers
Classifier: License :: OSI Approved :: MIT License
Classifier: Operating System :: OS Independent
Classifier: Programming Language :: Python
Classifier: Programming Language :: Python :: 3
Classifier: Programming Language :: Python :: 3.7
Classifier: Programming Language :: Python :: 3.8
Classifier: Programming Language :: Python :: 3.9
Classifier: Programming Language :: Python :: 3.10
Requires-Dist: requests
